LICENSE.txt
MANIFEST.in
README.rst
setup.py
NewlineJSON.egg-info/PKG-INFO
NewlineJSON.egg-info/SOURCES.txt
NewlineJSON.egg-info/dependency_links.txt
NewlineJSON.egg-info/requires.txt
NewlineJSON.egg-info/top_level.txt
NewlineJSON.egg-info/zip-safe
newlinejson/__init__.py
newlinejson/core.py
newlinejson/deprecated.py
newlinejson/pycompat.py
tests/__init__.py
tests/data.py
tests/test_core.py
tests/test_deprecated.py