Metadata-Version: 1.1
Name: NewlineJSON
Version: 0.3.2
Summary: Streaming newline delimited JSON I/O with transparent compression
Home-page: https://github.com/geowurster/NewlineJSON
Author: Kevin Wurster
Author-email: wursterk@gmail.com
License: New BSD License
